infi8/__init__.py
infi8/arithmetic.py
infi8/geometric.py
infi8/harmonic.py
infi8-0.1.2.dist-info/METADATA
infi8-0.1.2.dist-info/WHEEL
infi8-0.1.2.dist-info/top_level.txt
infi8-0.1.2.dist-info/RECORD
