Metadata-Version: 2.4
Name: infi8
Version: 0.1.2
Summary: A package for working with infinite, arithmetic, geometric, and harmonic series.
Author: Venkata Srinivas Babu Oguri
Author-email: srinivasoguri19@gmail.com
Dynamic: author
Dynamic: author-email
Dynamic: summary
